liesel_gam/__about__.py
liesel_gam/__init__.py
liesel_gam/basis.py
liesel_gam/basis_builder.py
liesel_gam/category_mapping.py
liesel_gam/consolidate_bases.py
liesel_gam/constraint.py
liesel_gam/demo_data.py
liesel_gam/dist.py
liesel_gam/io.py
liesel_gam/kernel.py
liesel_gam/names.py
liesel_gam/plots.py
liesel_gam/predictor.py
liesel_gam/registry.py
liesel_gam/summary.py
liesel_gam/term.py
liesel_gam/term_builder.py
liesel_gam/var.py
liesel_gam/experimental/__init__.py
liesel_gam/experimental/approx_bspline.py
liesel_gam-0.1.0.dist-info/METADATA
liesel_gam-0.1.0.dist-info/WHEEL
liesel_gam-0.1.0.dist-info/licenses/LICENSE
liesel_gam-0.1.0.dist-info/RECORD
