Metadata-Version: 2.4
Name: liesel_gam
Version: 0.1.0
Summary: Functionality for Generalized Additive Models in Liesel
Author: Johannes Brachem
License-File: LICENSE
Keywords: machine-learning,statistics
Classifier: Intended Audience :: Science/Research
Classifier: License :: OSI Approved :: MIT License
Classifier: Programming Language :: Python :: 3
Classifier: Programming Language :: Python :: 3.13
Requires-Python: <3.14,>=3.13
Requires-Dist: formulaic>=1.2.1
Requires-Dist: liesel>=0.4.2
Requires-Dist: plotnine>=0.14.5
Requires-Dist: smoothcon>=0.0.9
